simple_amqp_pubsub/__init__.py
simple_amqp_pubsub/asyncio.py
simple_amqp_pubsub/consts.py
simple_amqp_pubsub/data.py
simple_amqp_pubsub/encoding.py
simple_amqp_pubsub/gevent.py
simple_amqp_pubsub/log.py
simple_amqp_pubsub/subscriber.py
simple_amqp_pubsub/base/__init__.py
simple_amqp_pubsub/base/amqp.py
simple_amqp_pubsub/base/client.py
simple_amqp_pubsub/base/conn.py
simple_amqp_pubsub-0.4.3.dist-info/METADATA
simple_amqp_pubsub-0.4.3.dist-info/RECORD
simple_amqp_pubsub-0.4.3.dist-info/WHEEL
simple_amqp_pubsub-0.4.3.dist-info/top_level.txt
