Metadata-Version: 2.1
Name: simple-amqp-pubsub
Version: 0.4.3
Summary: Simple AMQP Pub/Sub lib
Home-page: https://github.com/rudineirk/py-simple-amqp-pubsub
Author: Rudinei Goi Roecker
Author-email: rudinei.roecker@gmail.com
License: MIT
Keywords: simple amqp pubsub
Platform: UNKNOWN
Classifier: Development Status :: 3 - Alpha
Classifier: Intended Audience :: Developers
Classifier: Topic :: Software Development :: Libraries :: Application Frameworks
Classifier: License :: OSI Approved :: MIT License
Classifier: Programming Language :: Python :: 3
Classifier: Programming Language :: Python :: 3.6
Provides-Extra: asyncio
Provides-Extra: gevent
Requires-Dist: simple-amqp (>=0.2.2)
Requires-Dist: msgpack
Provides-Extra: asyncio
Requires-Dist: aio-pika; extra == 'asyncio'
Provides-Extra: gevent
Requires-Dist: gevent; extra == 'gevent'
